{"minimum_required":"v4.0.0","stage_name":"camp_r_28","actions":[{"type":"SpeedUp"},{"type":"Deploy","name":"史尔特尔","location":[6,4],"direction":"Left"},{"type":"Deploy","name":"娜仁图亚","location":[7,3],"direction":"Left"},{"type":"Deploy","name":"林","direction":"Right","location":[8,4]},{"type":"Deploy","name":"瑕光","location":[6,3],"direction":"Left"},{"type":"Deploy","name":"早露","location":[5,2],"direction":"Down"},{"type":"Deploy","name":"阿米娅","location":[6,5],"direction":"Right"}],"doc":{"title":"萨尔贡 - 大巴扎 - 大巴扎","details":"萨尔贡 - 大巴扎 - 大巴扎    自己用自己用"},"groups":[],"opers":[{"name":"史尔特尔"},{"name":"银灰"},{"name":"娜仁图亚"},{"name":"克洛丝"},{"name":"寒芒克洛丝"},{"name":"早露"},{"name":"玛恩纳"},{"name":"瑕光"},{"name":"伊芙利特"},{"name":"阿米娅"},{"name":"林","skill_usage":1,"skill":3}]}