{"minimum_required":"v4.0.0","stage_name":"wk_melee_6","actions":[{"type":"Deploy","name":"维什戴尔","location":[5,2],"direction":"Right"},{"type":"Deploy","name":"角峰","location":[6,2],"direction":"Right"},{"type":"SpeedUp"},{"type":"Deploy","direction":"Right","name":"黑角","location":[6,1]},{"type":"Skill","kills":4,"pre_delay":1000,"rear_delay":0,"name":"维什戴尔","location":[5,2]},{"type":"Deploy","name":"芙蓉","location":[4,2],"direction":"Right"},{"type":"Deploy","direction":"Right","kills":17,"pre_delay":6000,"rear_delay":1000,"name":"砾","location":[4,4]},{"type":"Retreat","kills":24,"name":"砾"},{"type":"Deploy","name":"玫兰莎","location":[4,4],"direction":"Right"},{"type":"Skill","kills":28,"pre_delay":0,"rear_delay":0,"name":"维什戴尔","location":[5,2]},{"type":"Deploy","name":"安赛尔","location":[4,1],"direction":"Right"},{"type":"Skill","kills":39,"pre_delay":0,"name":"角峰"},{"type":"Skill","name":"芙蓉","kills":39},{"type":"SkillDaemon"}],"doc":{"title":"货物运送 - CE-6 - 实验原件押运(自用)","details":"30级芙蓉、1级玫兰莎、45级角峰、1级砾、1级安塞尔、30级黑角、助战精二维什戴尔。"},"groups":[],"opers":[{"name":"芙蓉","skill":1,"skill_usage":0},{"name":"角峰","skill":1,"skill_usage":0},{"name":"砾","skill":1,"skill_usage":0},{"name":"安赛尔","skill":1,"skill_usage":0},{"name":"黑角","skill":1,"skill_usage":0},{"name":"维什戴尔","skill":3,"skill_usage":0},{"name":"玫兰莎","skill":1,"skill_usage":0}]}