{"stage_name":"act2break_10","minimum_required":"v4.0.0","doc":{"title":"VEC-10 - 涣散喧嚣","details":"需要启用补给：\n疗愈装备、扰动装备\n⬛🟨⬛⬛\n⬛🟨⬛⬛\n⬛⬛⬛⬛\n⬛⬛⬛⬛\n\n参考视频：【VEC-10  雪遥银三核  摆完挂机】 https://www.bilibili.com/video/BV1bGf4BKELs/?share_source=copy_web&vd_source=41590d54f87e4899f343a5c6c01e0b29\n\nUP主：樰本爱\n\nJson作者：水岙\n\n测试练度：29033遥，26233圣聆初雪，2623凛御银灰，1727黍\n不带德克萨斯的话阻挡的费用不要超过20不然可能来不及阻挡会漏怪"},"opers":[{"name":"遥","skill":2,"skill_usage":1,"requirements":{"elite":2,"level":90,"skill_level":10,"module":2}},{"name":"圣聆初雪","skill":2,"skill_usage":0,"requirements":{"elite":2,"level":62,"skill_level":10,"module":2}},{"name":"凛御银灰","skill":3,"skill_usage":1,"requirements":{"level":62,"skill_level":10}}],"groups":[{"name":"阻挡","opers":[{"name":"黍","skill":1,"requirements":{"elite":1,"level":72,"skill_level":7,"module":-1}},{"name":"卡缇","skill":1,"skill_usage":1,"requirements":{"skill_level":7}}]},{"name":"开局加费（带了更稳）","opers":[{"name":"德克萨斯","skill":1,"requirements":{"level":42,"skill_level":7,"module":-1}}]}],"actions":[{"type":"SpeedUp"},{"name":"遥","location":[1,1],"direction":"Down","type":"Deploy"},{"name":"阻挡","location":[2,3],"direction":"Right","type":"Deploy"},{"name":"凛御银灰","location":[2,2],"direction":"Right","type":"Deploy"},{"name":"圣聆初雪","location":[3,1],"direction":"Down","type":"Deploy"},{"type":"SkillDaemon"}],"version":3}