{"stage_name":"act2break_09","minimum_required":"v4.0.0","doc":{"title":"VEC-09 - 紧急逃生","details":"VEC-09 - 紧急逃生"},"opers":[{"name":"遥","skill":2,"skill_usage":2,"skill_times":2,"requirements":{"skill_level":7,"module":2}},{"name":"圣聆初雪","skill":2,"requirements":{"skill_level":10,"module":2}},{"name":"维什戴尔","skill":3,"skill_usage":1,"requirements":{"skill_level":10,"module":1}},{"name":"娜仁图亚","skill":3,"skill_usage":1,"requirements":{"skill_level":10,"module":1}}],"groups":[],"actions":[{"name":"圣聆初雪","location":[4,4],"direction":"Right","type":"Deploy","costs":0},{"name":"遥","location":[3,2],"direction":"Down","type":"Deploy"},{"type":"SpeedUp"},{"name":"娜仁图亚","location":[5,4],"direction":"Up","type":"Deploy"},{"name":"维什戴尔","location":[6,4],"direction":"Left","type":"Deploy"},{"type":"SkillDaemon"}],"version":3}