{"minimum_required":"v4.0.0","stage_name":"act2break_sp14","actions":[{"type":"Deploy","name":"银灰","direction":"Up","location":[4,3]},{"type":"Deploy","name":"夜刀","direction":"Up","location":[5,2]},{"type":"SpeedUp"},{"type":"Retreat","name":"银灰","kills":9},{"type":"Retreat","name":"夜刀"},{"type":"Deploy","name":"银灰","direction":"Left","location":[5,1]},{"type":"Deploy","name":"夜刀","direction":"Left","location":[5,2]},{"type":"SkillDaemon"}],"doc":{"title":"VEC-SP12 - 水土不服","details":" json作者：萨拉托加\n作业交流群https://qm.qq.com/q/fOTd25vGWk ，可蹲作业，有问题进群找我，作业站消息没提醒看不到"},"groups":[],"opers":[{"name":"银灰","skill":3,"skill_usage":1},{"name":"夜刀","skill":1,"skill_usage":0}]}