{"stage_name":"act38side_07","minimum_required":"v4.0.0","doc":{"title":"PV-7 - 揭幕时刻 银灰初雪双人","details":"银灰2603 三技能 强烈建议三技能专三 不然会出现奇怪的轴\n初雪2603 二技能无模组测试可过 练度越高越好\n携带增伤烟花"},"opers":[{"name":"凛御银灰","skill":3,"skill_usage":1,"requirements":{"skill_level":10}},{"name":"Lancet-2"},{"name":"圣聆初雪","skill":2,"requirements":{"skill_level":10}},{"name":"卡缇","skill":1,"skill_usage":1,"requirements":{"skill_level":7}}],"groups":[],"actions":[{"name":"凛御银灰","location":[10,6],"direction":"Up","type":"Deploy","costs":14},{"type":"Skill","name":"凛御银灰","location":[10,6],"cost_changes":5},{"name":"圣聆初雪","location":[9,5],"direction":"Right","type":"Deploy","pre_delay":500},{"type":"SpeedUp"},{"name":"卡缇","location":[10,5],"direction":"Up","type":"Deploy","costs":30},{"type":"SkillDaemon"}],"version":3}