{"stage_name":"act18side_ex04","minimum_required":"v4.0.0","doc":{"title":"尘影余音 - LE-EX-4 - 双手练习（Marcus自用）","details":"尘影余音 - LE-EX-4 - 双手练习（Marcus自用）"},"opers":[{"name":"圣聆初雪","skill":2,"skill_usage":0},{"name":"凛御银灰","skill":3,"skill_usage":1},{"name":"Friston-3","skill":1,"skill_usage":0},{"name":"遥","skill":2,"skill_usage":1},{"name":"纯烬艾雅法拉","skill":1,"skill_usage":0}],"groups":[],"actions":[{"type":"SpeedUp"},{"name":"凛御银灰","location":[6,3],"direction":"Up","type":"Deploy"},{"type":"Skill","name":"凛御银灰"},{"name":"圣聆初雪","location":[5,2],"direction":"Right","type":"Deploy"},{"name":"遥","location":[4,2],"direction":"Right","type":"Deploy"},{"name":"纯烬艾雅法拉","location":[4,4],"direction":"Up","type":"Deploy"}],"difficulty":2}