{"stage_name":"act44side_ex03","minimum_required":"v4.0.0","doc":{"title":"AT-EX-3 - 浪切浴场","details":"孑诺 https://www.bilibili.com/video/BV1FVtezSEsT?p=3"},"opers":[{"name":"艾雅法拉","skill":2,"requirements":{"skill_level":10}},{"name":"逻各斯","skill":1,"requirements":{"skill_level":10}},{"name":"棘刺","skill":3,"skill_usage":1,"requirements":{"skill_level":10}},{"name":"德克萨斯","skill":1,"requirements":{"skill_level":7}}],"groups":[{"name":"塞或黍","opers":[{"name":"塞雷娅","skill":1,"requirements":{"skill_level":10}},{"name":"黍","skill":1,"requirements":{"skill_level":10}}]}],"actions":[{"name":"德克萨斯","location":[9,4],"direction":"Left","type":"Deploy"},{"type":"SpeedUp"},{"type":"Skill","name":"天命来袭","location":[7,1],"cost_changes":6},{"name":"棘刺","location":[8,3],"direction":"Down","type":"Deploy"},{"name":"逻各斯","location":[6,2],"direction":"Down","type":"Deploy"},{"name":"塞或黍","location":[8,4],"direction":"Left","type":"Deploy"},{"name":"艾雅法拉","location":[2,4],"direction":"Right","type":"Deploy"},{"type":"SkillDaemon"}],"version":3}