{"minimum_required":"v4.0.0","stage_name":"camp_r_12","actions":[{"type":"Deploy","name":"先锋1","location":[10,3],"direction":"Left"},{"type":"Deploy","name":"先锋2","location":[10,4],"direction":"Left"},{"type":"Deploy","name":"速狙2","location":[7,6],"direction":"Left"},{"type":"Deploy","name":"奶盾","location":[6,3],"direction":"Down"},{"type":"SpeedUp"},{"type":"Deploy","name":"遥","location":[5,2],"direction":"Down"},{"type":"Deploy","name":"速狙1","direction":"Up","location":[10,6]},{"type":"Deploy","name":"奶2","location":[8,2],"direction":"Left"},{"type":"Deploy","name":"奶1","location":[9,5],"direction":"Left"},{"type":"Deploy","name":"元素奶","location":[9,2],"direction":"Left"},{"type":"Retreat","name":"速狙2","location":[7,6],"kills":11},{"type":"Deploy","name":"盾2","location":[6,4],"direction":"Down"},{"type":"Deploy","name":"奶盾2","location":[6,1],"direction":"Down"},{"type":"Retreat","location":[10,3],"name":"先锋2","kills":21},{"type":"Deploy","name":"速狙2","location":[9,6],"direction":"Left"},{"type":"Retreat","costs":30,"name":"先锋1","location":[10,4]},{"type":"Deploy","name":"盾1","location":[5,1],"direction":"Right"}],"doc":{"title":"拉特兰 - 巧克力大街 遥","details":"低配没有测试过，高配有调整序列以及加了费用判断应该不会卡费，自测能用\n原作者：低配挂机研讨会\njson作者：玄乙\n原视频链接：【新的时代】从此删除巧克力大街 单核挂机攻略-哔哩哔哩】 https://b23.tv/XgTBrl5"},"groups":[{"name":"盾1","opers":[{"name":"余","skill":1,"skill_usage":1},{"name":"星熊","skill":2,"skill_usage":0}]},{"name":"奶盾","opers":[{"name":"古米","skill":1,"skill_usage":0},{"name":"临光","skill":1,"skill_usage":0},{"name":"塞雷娅","skill":1,"skill_usage":0},{"name":"黍","skill":1,"skill_usage":0}]},{"name":"奶盾2","opers":[{"name":"古米","skill":1,"skill_usage":0},{"name":"临光","skill":1,"skill_usage":0},{"name":"塞雷娅","skill":1,"skill_usage":0},{"name":"黍","skill":1,"skill_usage":0},{"name":"山","skill":2,"skill_usage":2,"skill_times":1}]},{"name":"奶1","opers":[{"name":"闪灵","skill":2,"skill_usage":0},{"name":"安赛尔","skill_usage":1,"skill":1}]},{"name":"元素奶","opers":[{"name":"蜜莓","skill":1,"skill_usage":0},{"name":"纯烬艾雅法拉","skill":1,"skill_usage":0}]},{"name":"先锋1","opers":[{"name":"芬","skill":1,"skill_usage":0},{"name":"香草","skill":1,"skill_usage":1},{"name":"桃金娘","skill":1,"skill_usage":1}]},{"name":"先锋2","opers":[{"name":"讯使","skill":1,"skill_usage":0},{"name":"德克萨斯","skill":1,"skill_usage":0}]},{"name":"速狙1","opers":[{"name":"梅","skill":1,"skill_usage":0},{"skill_times":1,"name":"娜仁图亚","skill_usage":2,"skill":1}]},{"name":"速狙2","opers":[{"name":"能天使","skill":3,"skill_usage":0}]},{"name":"盾2","opers":[{"name":"角峰","skill":2,"skill_usage":1},{"name":"斩业星熊","skill":2,"skill_usage":0}]},{"name":"奶2","opers":[{"name":"流明","skill":3,"skill_usage":1}]}],"opers":[{"name":"遥","skill":2,"skill_usage":1}]}