{"stage_name":"act41side_01","minimum_required":"v4.0.0","doc":{"title":"EA-1 - 扉页所见 胆鸟双人","details":"给胆鸟妹胆鸟哥解放双手的作业，欢迎使用，祝这对好兄弟情侣99\n默认满练，潜能无所谓。\n"},"opers":[{"name":"棘刺","skill":3,"skill_usage":1,"requirements":{"level":90,"skill_level":10,"module":4}},{"name":"极境","skill":1,"skill_usage":2,"requirements":{"level":80,"skill_level":10,"module":1}}],"groups":[],"actions":[{"name":"棘刺","location":[4,5],"direction":"Up","type":"Deploy","costs":0},{"name":"极境","location":[3,5],"direction":"Right","type":"Deploy","cost_changes":0},{"type":"SpeedUp"},{"type":"SkillDaemon"}],"version":3}