{"stage_name":"act13side_tr02","minimum_required":"v4.0.0","doc":{"title":"长夜临光·复刻 - NL-TR-2 - 骑士流氓","details":"2"},"opers":[],"groups":[],"actions":[{"type":"SpeedUp","costs":19,"pre_delay":2000},{"type":"SpeedUp","pre_delay":1000},{"type":"SpeedUp","costs":26,"pre_delay":2000},{"type":"SpeedUp","pre_delay":1000},{"type":"SpeedUp","costs":43,"pre_delay":2000},{"type":"SpeedUp","pre_delay":1000},{"type":"SpeedUp","pre_delay":1000},{"type":"SpeedUp","pre_delay":1000},{"type":"SpeedUp","pre_delay":1000},{"type":"SpeedUp","costs":47,"pre_delay":2000},{"type":"SpeedUp","pre_delay":1000},{"name":"骑士之徽","location":[7,5],"direction":"None","type":"Deploy"},{"name":"安赛尔","location":[7,5],"direction":"Up","type":"Deploy"},{"name":"史都华德","location":[7,4],"direction":"Up","type":"Deploy"},{"type":"SpeedUp"},{"type":"Skill","location":[1,5]},{"type":"SkillDaemon"}],"version":3}