{"stage_name":"act16d5_09","minimum_required":"v4.0.0","doc":{"title":"画中人·复刻 - WR-9 - 观花 - 令","details":"JSON作者：小卡拉帕鲁灰，B站同名\n本作业已开启截图增强\n求关注。"},"opers":[{"name":"令","skill":3,"skill_usage":1,"requirements":{"elite":2,"level":90,"module":2}},{"name":"夜刀"}],"groups":[],"actions":[{"name":"令","location":[5,6],"direction":"Up","type":"Deploy"},{"name":"“弦惊”","location":[4,6],"direction":"Up","type":"Deploy"},{"name":"“弦惊”","location":[3,2],"direction":"Right","type":"Deploy"},{"type":"SpeedUp"},{"name":"“弦惊”","location":[4,5],"direction":"Right","type":"Deploy"},{"name":"“弦惊”","location":[2,2],"direction":"Right","type":"Deploy"},{"name":"“弦惊”","location":[6,4],"direction":"Left","type":"Deploy"},{"name":"“弦惊”","location":[7,4],"direction":"Left","type":"Deploy"},{"name":"“弦惊”","location":[5,4],"direction":"Up","type":"Deploy"},{"type":"SkillDaemon"}],"version":3}