{"stage_name":"act45side_06","minimum_required":"v4.0.0","doc":{"title":"SS-6 - 回声飘荡的大厅","details":"由于维什戴尔的概率问题，有极小概率需要重试"},"opers":[{"name":"维什戴尔","skill":3,"skill_usage":0,"requirements":{"skill_level":10}}],"groups":[],"actions":[{"type":"SpeedUp"},{"name":"维什戴尔","location":[5,4],"direction":"Left","type":"Deploy"},{"type":"Skill","name":"维什戴尔","kills":4},{"type":"Skill","name":"维什戴尔","kills":12,"pre_delay":3000},{"type":"Skill","name":"维什戴尔","kills":15,"pre_delay":1000},{"type":"Skill","name":"维什戴尔","kills":20},{"name":"维什戴尔","skill_usage":1,"type":"SkillUsage"},{"type":"SkillDaemon"}],"version":3}