{"minimum_required":"v4.0.0","stage_name":"act25side_ex07","actions":[{"type":"SpeedUp"},{"type":"Deploy","kills":0,"name":"棘刺","direction":"Right","location":[1,5]},{"type":"Deploy","name":"逻各斯","location":[7,5],"direction":"Left"},{"type":"Skill","name":"逻各斯","location":[7,5],"kills":8},{"type":"Skill","kills":19,"name":"逻各斯","location":[7,5]}],"doc":{"title":"孤星 - CW-EX-7 - 前线模拟","details":"【CW-EX-7逻棘双人】 https://www.bilibili.com/video/BV1u7421o72N/?share_source=copy_web&vd_source=903d1b1a534dc8c7754affe0ebbf33f6"},"groups":[],"opers":[{"name":"棘刺","skill":3,"skill_usage":1},{"name":"逻各斯","skill_usage":0,"skill":3}],"difficulty":1}