{"stage_name":"sub_05-2-2","minimum_required":"v4.0.0","doc":{"title":"第五章 靶向药物 - S5-4 - 恶寒-2 低配","details":"【苏咕咕】明日方舟 S5-4 攻略 简单 无脑 抄作业 | 作者：苏咕咕酱\nhttps://www.bilibili.com/video/BV1jV4116775"},"opers":[{"name":"芬"},{"name":"克洛丝"},{"name":"月见夜"},{"name":"杰西卡","skill":1,"requirements":{"skill_level":7}},{"name":"炎熔"},{"name":"安赛尔"},{"name":"Lancet-2"},{"name":"芙蓉"},{"name":"阿米娅","skill":1,"skill_usage":1,"requirements":{"skill_level":7}}],"groups":[],"actions":[{"name":"芬","location":[7,3],"direction":"Left","type":"Deploy"},{"type":"SpeedUp"},{"name":"克洛丝","location":[3,3],"direction":"Right","type":"Deploy"},{"name":"月见夜","location":[3,4],"direction":"Right","type":"Deploy"},{"name":"杰西卡","location":[5,5],"direction":"Up","type":"Deploy"},{"name":"炎熔","location":[7,4],"direction":"Left","type":"Deploy"},{"name":"安赛尔","location":[6,5],"direction":"Up","type":"Deploy"},{"name":"干扰装置","location":[4,3],"direction":"None","type":"Deploy"},{"name":"Lancet-2","location":[4,2],"direction":"Down","type":"Deploy"},{"name":"干扰装置","location":[6,4],"direction":"None","type":"Deploy"},{"type":"SpeedUp","costs":17},{"type":"Retreat","name":"Lancet-2"},{"type":"BulletTime","location":[3,3]},{"name":"芙蓉","location":[4,2],"direction":"Down","type":"Deploy"},{"type":"SpeedUp"},{"name":"炎熔","skill_usage":2,"type":"SkillUsage","kills":32},{"name":"月见夜","skill_usage":2,"type":"SkillUsage"},{"name":"阿米娅","location":[5,2],"direction":"Down","type":"Deploy"},{"name":"安赛尔","skill_usage":1,"type":"SkillUsage","kills":46},{"name":"月见夜","skill_usage":1,"type":"SkillUsage"},{"name":"炎熔","skill_usage":1,"type":"SkillUsage"},{"name":"芙蓉","skill_usage":1,"type":"SkillUsage"},{"type":"SkillDaemon"}],"version":3}