{"stage_name":"tough_13-08","minimum_required":"v4.0.0","doc":{"title":"第十三章 恶兆湍流 - 13-10（磨难） - 幻境迁流","details":"第十三章 恶兆湍流 - 13-10（磨难） - 幻境迁流"},"opers":[{"name":"香草","skill":1,"skill_usage":1,"requirements":{"skill_level":7}},{"name":"芬","skill":1,"requirements":{"skill_level":7}},{"name":"圣聆初雪","skill":2,"requirements":{"skill_level":10,"module":2}},{"name":"遥","skill":2,"skill_usage":1,"requirements":{"skill_level":10,"module":2}}],"groups":[],"actions":[{"type":"SpeedUp"},{"name":"香草","location":[7,3],"direction":"Left","type":"Deploy"},{"name":"芬","location":[7,6],"direction":"Left","type":"Deploy"},{"name":"遥","location":[7,5],"direction":"Left","type":"Deploy"},{"name":"圣聆初雪","location":[5,4],"direction":"Down","type":"Deploy"},{"type":"Skill","location":[5,6],"costs":12},{"type":"SkillDaemon"}],"version":3}