{"minimum_required":"v4.0.0","stage_name":"act15d0_ex08","actions":[{"type":"SpeedUp"},{"type":"Deploy","costs":0,"name":"遥","direction":"Left","location":[4,4]},{"type":"Deploy","costs":0,"name":"乌尔比安","direction":"Right","location":[3,5]},{"type":"Deploy","costs":0,"name":"斩业星熊","direction":"Up","location":[3,3]},{"type":"Deploy","costs":0,"name":"歌蕾蒂娅","direction":"Up","location":[3,4]},{"type":"SkillDaemon"}],"doc":{"title":"孤岛风云·复刻 - MB-EX-8 - 先到先得","details":"超大杯挂机，德狗带不带应该无所谓"},"groups":[],"opers":[{"name":"乌尔比安","skill":2,"skill_usage":0},{"name":"歌蕾蒂娅","skill":1,"skill_usage":0},{"name":"斩业星熊","skill":1,"skill_usage":0},{"name":"遥","skill":2,"skill_usage":1},{"name":"德克萨斯","skill":1,"skill_usage":0}],"difficulty":3}