{"stage_name":"act12side_02","minimum_required":"v4.0.0","doc":{"title":"多索雷斯假日·复刻 - DH-2 - 首轮竞赛 - 单核","details":"令满级，专3，三级模组\n持续更新中，作业交流群789724611，如果作业有问题可以加群找我，评论区不能及时回复"},"opers":[{"name":"令","skill":3,"skill_usage":1,"requirements":{"elite":2,"level":90,"module":2}},{"name":"夜刀"}],"groups":[],"actions":[{"name":"令","location":[7,2],"direction":"Left","type":"Deploy"},{"name":"“弦惊”","location":[8,1],"direction":"Left","type":"Deploy"},{"type":"SpeedUp"},{"name":"“弦惊”","location":[6,5],"direction":"Left","type":"Deploy"},{"name":"“弦惊”","location":[7,5],"direction":"Left","type":"Deploy"},{"name":"“弦惊”","location":[7,1],"direction":"Left","type":"Deploy"},{"name":"“弦惊”","location":[3,3],"direction":"Right","type":"Deploy"},{"name":"“弦惊”","location":[3,2],"direction":"Down","type":"Deploy"},{"type":"SkillDaemon"}],"version":3}