{"stage_name":"act48side_05","minimum_required":"v4.0.0","doc":{"title":"ME-5 - 汇流","details":"https://www.bilibili.com/video/BV19jrNB3Ed3/?spm_id_from=333.337.search-card.all.click&vd_source=d47099876be977946e63a23a39e12485"},"opers":[{"name":"娜仁图亚","skill":1,"skill_usage":2,"requirements":{"skill_level":10}},{"name":"乌尔比安","skill":2,"requirements":{"skill_level":10}},{"name":"歌蕾蒂娅","skill":2,"requirements":{"skill_level":10}}],"groups":[],"actions":[{"type":"SpeedUp"},{"name":"乌尔比安","location":[4,2],"direction":"Left","type":"Deploy"},{"name":"歌蕾蒂娅","location":[5,2],"direction":"Left","type":"Deploy"},{"name":"娜仁图亚","location":[8,2],"direction":"Down","type":"Deploy"},{"type":"SkillDaemon"}],"version":3}