{"stage_name":"act2break_sp05","minimum_required":"v4.0.0","doc":{"title":"VEC-SP05 - 污染危机","details":"参考视频：https://www.bilibili.com/video/BV1QCfsBKEa6"},"opers":[{"name":"多萝西","skill":2,"requirements":{"skill_level":7}}],"groups":[],"actions":[{"name":"多萝西","location":[8,3],"direction":"Left","type":"Deploy"},{"type":"SpeedUp"},{"name":"共振装置","location":[5,2],"direction":"None","type":"Deploy"},{"name":"共振装置","location":[5,3],"direction":"None","type":"Deploy"},{"name":"共振装置","location":[7,2],"direction":"None","type":"Deploy"},{"name":"共振装置","location":[5,2],"direction":"None","type":"Deploy","kills":1},{"name":"共振装置","location":[5,3],"direction":"None","type":"Deploy","kills":2},{"name":"共振装置","location":[5,2],"direction":"None","type":"Deploy","kills":3},{"name":"共振装置","location":[5,2],"direction":"None","type":"Deploy","kills":4},{"name":"共振装置","location":[5,3],"direction":"None","type":"Deploy","kills":5},{"name":"共振装置","location":[5,2],"direction":"None","type":"Deploy","kills":6},{"name":"共振装置","location":[5,3],"direction":"None","type":"Deploy","kills":7},{"name":"共振装置","location":[6,2],"direction":"None","type":"Deploy","kills":8},{"name":"共振装置","location":[5,2],"direction":"None","type":"Deploy","kills":10},{"name":"共振装置","location":[5,2],"direction":"None","type":"Deploy","cost_changes":6},{"name":"共振装置","location":[7,2],"direction":"None","type":"Deploy","kills":12},{"name":"共振装置","location":[2,1],"direction":"None","type":"Deploy"},{"name":"共振装置","location":[3,1],"direction":"None","type":"Deploy"},{"name":"共振装置","location":[4,1],"direction":"None","type":"Deploy"},{"type":"SkillDaemon"}],"version":3}