{"minimum_required":"v4.0.0","stage_name":"tough_12-17","actions":[{"type":"SpeedUp"},{"type":"Deploy","name":"速射手","direction":"Up","location":[2,2]},{"type":"Deploy","name":"维什戴尔","location":[7,4],"direction":"Right"},{"type":"SkillUsage","name":"维什戴尔","skill_usage":2,"skill_times":1},{"type":"Deploy","name":"阿米娅","direction":"Down","location":[5,3]},{"type":"Deploy","name":"塞雷娅","direction":"Right","location":[4,6]},{"type":"Skill","name":"维什戴尔","location":[7,4],"kills":2},{"type":"SkillUsage","name":"维什戴尔","skill_usage":2,"skill_times":1},{"type":"Deploy","name":"蛇屠箱","direction":"Right","location":[7,6]},{"type":"Deploy","name":"调香师","location":[6,5],"direction":"Left"},{"type":"Deploy","name":"锏","direction":"Left","location":[5,5]},{"type":"SkillUsage","name":"维什戴尔","skill_usage":2,"skill_times":1},{"type":"Deploy","name":"玫兰莎","location":[9,6],"direction":"Right","kills":7},{"type":"SkillDaemon"}],"doc":{"title":"第十二章 惊霆无声 - 12-19（磨难） - 飞跃，烟火","details":"原作者：低配挂机研讨会\n\n视频地址：https://www.bilibili.com/video/BV1rFVjzeEZm?spm_id_from=333.788.videopod.sections&vd_source=a022f0b9420b7e9fe33605d41aed4c75&p=107\n阿米娅是吉祥物\n维什戴尔90级 三技能专三 三级模组"},"groups":[{"name":"速射手","opers":[{"name":"新约能天使","skill":3,"skill_usage":1},{"name":"克洛丝","skill":1,"skill_usage":0}]}],"opers":[{"name":"阿米娅","skill":1,"skill_usage":1},{"name":"维什戴尔","skill":3,"skill_usage":0},{"name":"锏","skill":3,"skill_usage":1},{"name":"塞雷娅","skill":1,"skill_usage":0},{"name":"调香师","skill":2,"skill_usage":1},{"name":"玫兰莎","skill":1,"skill_usage":1},{"name":"蛇屠箱","skill":2,"skill_usage":1}]}