{"stage_name":"tough_13-19","minimum_required":"v6.0.0","doc":{"title":"第十三章 恶兆湍流 - 13-21（磨难） - 殷红君主","details":"已通过测试 角色练度为测试练度 不保证最低\n\n清场后会有非常长的打年糕时间，可以通过依照提示手动释放炸弹/携带其他攻击干员加速进程。"},"opers":[{"name":"圣聆初雪","skill":2,"skill_usage":0,"requirements":{"level":90}},{"name":"凛御银灰","skill":3,"skill_usage":2},{"name":"遥","skill":2,"skill_usage":1,"requirements":{"level":90}},{"name":"乌尔比安","skill":2,"skill_usage":0,"requirements":{"elite":2,"level":90}}],"groups":[{"name":"换费","opers":[{"name":"Castle-3"},{"name":"Lancet-2"},{"name":"CONFESS-47"},{"name":"PhonoR-0"},{"name":"THRM-EX"},{"name":"Friston-3"},{"name":"正义骑士号"},{"name":"U-Official"}]}],"actions":[{"type":"SpeedUp"},{"name":"凛御银灰","location":[8,3],"direction":"Left","type":"Deploy"},{"name":"遥","location":[7,6],"direction":"Up","type":"Deploy"},{"name":"圣聆初雪","location":[7,4],"direction":"Up","type":"Deploy"},{"name":"乌尔比安","location":[7,5],"direction":"Left","type":"Deploy"},{"type":"Skill","name":"炸弹","location":[10,3],"kills":18},{"type":"Output","doc":"在boss进入乌尔比安攻击范围后可以使用炸弹加速"},{"type":"SkillDaemon"}],"version":3}