{"stage_name":"main_05-10","minimum_required":"v4.0.0","doc":{"title":"第五章 靶向药物 - 5-10 - 长夜终尽 单核","details":"5-10突袭 遥单核5人 摆完挂机 | 作者：望星入梦\nhttps://www.bilibili.com/video/BV1kz4dz7Eyx\n——\n第五章作业合集：https://zoot.plus/?opset=37443"},"opers":[{"name":"遥","skill":2,"skill_usage":2,"skill_times":2,"requirements":{"skill_level":10}},{"name":"翎羽"},{"name":"泡普卡"},{"name":"玫兰莎","skill_usage":2,"skill_times":5},{"name":"月见夜","skill_usage":2,"skill_times":3},{"name":"米格鲁"}],"groups":[],"actions":[{"type":"SpeedUp"},{"name":"遥","location":[5,3],"direction":"Right","type":"Deploy"},{"name":"翎羽","location":[5,4],"direction":"Right","type":"Deploy"},{"type":"SpeedUp","costs":11},{"type":"Retreat","name":"翎羽"},{"type":"BulletTime","location":[5,3]},{"name":"泡普卡","location":[5,4],"direction":"Right","type":"Deploy"},{"type":"SpeedUp"},{"name":"玫兰莎","location":[7,4],"direction":"Right","type":"Deploy"},{"name":"月见夜","location":[7,3],"direction":"Down","type":"Deploy"},{"name":"米格鲁","location":[6,2],"direction":"Right","type":"Deploy"},{"name":"米格鲁","skill_usage":1,"type":"SkillUsage","kills":25},{"name":"泡普卡","skill_usage":2,"type":"SkillUsage","kills":67},{"type":"SkillDaemon"}],"version":3,"difficulty":3}