{"stage_name":"act45side_02","minimum_required":"v4.0.0","doc":{"title":"SS-2 - 寂静长廊的两端","details":"SS-2 - 寂静长廊的两端"},"opers":[{"name":"煌","skill":2,"requirements":{"skill_level":10}}],"groups":[{"name":"行医","opers":[{"name":"纯烬艾雅法拉","skill":1,"requirements":{"skill_level":10}},{"name":"蜜莓","skill":1,"requirements":{"skill_level":7}},{"name":"褐果","skill":1,"requirements":{"skill_level":7}}]}],"actions":[{"type":"SpeedUp"},{"name":"煌","location":[4,4],"direction":"Right","type":"Deploy"},{"name":"行医","location":[5,2],"direction":"Down","type":"Deploy"},{"type":"SkillDaemon"}],"version":3}