{"minimum_required":"v4.0.0","stage_name":"act11d0_07","actions":[{"type":"Deploy","name":"德克萨斯","location":[6,4],"direction":"Left"},{"type":"Deploy","name":"夜刀","location":[2,2],"direction":"Left"},{"type":"Deploy","name":"逻各斯","location":[4,3],"direction":"Down"},{"type":"Deploy","name":"新约能天使","location":[7,4],"direction":"Left"},{"type":"Deploy","name":"乌尔比安","location":[5,5],"direction":"Down"},{"type":"Deploy","name":"黍","location":[5,3],"direction":"Down"},{"type":"Deploy","name":"史尔特尔","location":[3,4],"direction":"Down"},{"type":"SpeedUp"},{"type":"SkillDaemon"}],"doc":{"title":"沃伦姆德的薄暮 - TW-7 - 群峦崩塌","details":"自用\n【【TW1至TW-EX-8】摆完挂机 简单好抄 +笔记隐藏关卡+信赖速刷攻略合集】 https://www.bilibili.com/video/BV1dg411g7np/?p=8&share_source=copy_web&vd_source=4488c6d30c638b20f5f6e91e6173a144"},"groups":[],"opers":[{"name":"德克萨斯","skill":1,"skill_usage":0},{"name":"夜刀","skill":1,"skill_usage":0},{"name":"史尔特尔","skill":1,"skill_usage":0},{"name":"逻各斯","skill":1,"skill_usage":0},{"name":"乌尔比安","skill":2,"skill_usage":0},{"name":"黍"},{"name":"新约能天使","skill":2,"skill_usage":1}]}