{"stage_name":"act35side_mo01","minimum_required":"v4.0.0","doc":{"title":"太阳甩在身后 - AS-MO-1 - 愿我们寻得安详","details":"太阳甩在身后 - AS-MO-1 - 愿我们寻得安详"},"opers":[{"name":"圣聆初雪","skill":2,"requirements":{"skill_level":10}},{"name":"怒潮凛冬","skill":2,"requirements":{"skill_level":10}}],"groups":[],"actions":[{"name":"怒潮凛冬","location":[4,5],"direction":"Left","type":"Deploy"},{"name":"圣聆初雪","location":[5,4],"direction":"Left","type":"Deploy"},{"type":"SpeedUp"},{"type":"SkillDaemon"}],"version":3,"difficulty":0}