{"stage_name":"act2break_06","minimum_required":"v4.0.0","doc":{"title":"VEC-06 - 灰烬游行团 - 无增益","details":"Json作者：水岙\n测试练度：29033乌尔比安，26213歌蕾蒂娅"},"opers":[{"name":"乌尔比安","skill":2,"skill_usage":0,"requirements":{"elite":2,"level":90,"skill_level":10,"module":1}},{"name":"歌蕾蒂娅","skill":1,"skill_usage":0,"requirements":{"elite":2,"level":62,"skill_level":8,"module":1}}],"groups":[],"actions":[{"type":"SpeedUp"},{"name":"歌蕾蒂娅","location":[1,2],"direction":"Down","type":"Deploy"},{"name":"乌尔比安","location":[1,4],"direction":"Down","type":"Deploy","costs":23},{"type":"SkillDaemon"}],"version":3}